pytekton/LICENSE.txt
pytekton/README.md
pytekton/__init__.py
pytekton/_seaborn.py
pytekton/bayesian.py
pytekton/capacity.py
pytekton/deprecate.py
pytekton/interesting_periods.py
pytekton/ipycompat.py
pytekton/perf_attrib.py
pytekton/plotting.py
pytekton/pos.py
pytekton/risk.py
pytekton/round_trips.py
pytekton/tears.py
pytekton/timeseries.py
pytekton/txn.py
pytekton/utils.py
pytekton-1.3.5.dist-info/LICENSE.txt
pytekton-1.3.5.dist-info/METADATA
pytekton-1.3.5.dist-info/WHEEL
pytekton-1.3.5.dist-info/top_level.txt
pytekton-1.3.5.dist-info/RECORD
