Metadata-Version: 2.1
Name: pytekton
Version: 1.3.5
Summary: PyFolio Tekton
Author: Quantopian and Everton Mendes
Author-email: emendes@tektonfinance.com
License-File: LICENSE.txt
Requires-Dist: pyfolio (>=0.9.2)
